{"mc":{"Icon_Animation_Wild":{"frameRate":30,"events":[],"frames":[{"res":"Icon_Animation_Wild_0","x":0,"y":0},{"res":"Icon_Animation_Wild_1","x":0,"y":0},{"res":"Icon_Animation_Wild_2","x":0,"y":0},{"res":"Icon_Animation_Wild_3","x":0,"y":0},{"res":"Icon_Animation_Wild_4","x":0,"y":0},{"res":"Icon_Animation_Wild_5","x":0,"y":0},{"res":"Icon_Animation_Wild_6","x":0,"y":0},{"res":"Icon_Animation_Wild_7","x":0,"y":0},{"res":"Icon_Animation_Wild_8","x":0,"y":0},{"res":"Icon_Animation_Wild_9","x":0,"y":0},{"res":"Icon_Animation_Wild_10","x":0,"y":0},{"res":"Icon_Animation_Wild_11","x":0,"y":0},{"res":"Icon_Animation_Wild_12","x":0,"y":0},{"res":"Icon_Animation_Wild_13","x":0,"y":0},{"res":"Icon_Animation_Wild_14","x":0,"y":0}]}},"res":{"Icon_Animation_Wild_13":{"x":392,"y":1436,"w":390,"h":357},"Icon_Animation_Wild_14":{"x":784,"y":359,"w":390,"h":357},"Icon_Animation_Wild_5":{"x":784,"y":718,"w":390,"h":357},"Icon_Animation_Wild_9":{"x":0,"y":359,"w":390,"h":357},"Icon_Animation_Wild_12":{"x":784,"y":0,"w":390,"h":357},"Icon_Animation_Wild_4":{"x":392,"y":718,"w":390,"h":357},"Icon_Animation_Wild_6":{"x":0,"y":718,"w":390,"h":357},"Icon_Animation_Wild_7":{"x":392,"y":0,"w":390,"h":357},"Icon_Animation_Wild_1":{"x":0,"y":0,"w":390,"h":357},"Icon_Animation_Wild_2":{"x":784,"y":1077,"w":390,"h":357},"Icon_Animation_Wild_0":{"x":0,"y":1436,"w":390,"h":357},"Icon_Animation_Wild_3":{"x":0,"y":1077,"w":390,"h":357},"Icon_Animation_Wild_8":{"x":392,"y":1077,"w":390,"h":357},"Icon_Animation_Wild_11":{"x":392,"y":359,"w":390,"h":357},"Icon_Animation_Wild_10":{"x":784,"y":1436,"w":390,"h":357}}}